items/CJKSGPItem.py
items/__init__.py
jk_sgp_lib/__init__.py
jk_sgp_lib/items/CJKSGPItem.py
jk_sgp_lib/items/__init__.py
jk_sgp_lib/msgs/CJKGSPTcMsgSender.py
jk_sgp_lib/msgs/__init__.py
jk_sgp_lib/pipelines/AbsJKSGPPipelineOfMysqlSaver.py
jk_sgp_lib/pipelines/__init__.py
jk_sgp_lib/spiders/AbsJKSGPSpider.py
jk_sgp_lib/spiders/__init__.py
pipelines/AbsJKSGPPipelineOfMysqlSaver.py
pipelines/__init__.py
spiders/AbsJKSGPSpider.py
spiders/__init__.py
jk_sgp_lib-1.6.1.dist-info/LICENSE
jk_sgp_lib-1.6.1.dist-info/METADATA
jk_sgp_lib-1.6.1.dist-info/WHEEL
jk_sgp_lib-1.6.1.dist-info/top_level.txt
jk_sgp_lib-1.6.1.dist-info/RECORD
