Metadata-Version: 2.1
Name: jk-sgp-lib
Version: 1.6.1
Summary: Make Scrapy easier and more versatile.
Home-page: https://github.com/kami1983/jk_sgp_lib
Author: kami1983
Author-email: kami@cancanyou.com
License: UNKNOWN
Platform: UNKNOWN
Requires-Python: >=2.7
Requires-Dist: scrapy
Requires-Dist: simplejson
Requires-Dist: pytz
Requires-Dist: pymysql
Requires-Dist: datetime
Requires-Dist: qcloudsms-py
